ant31box/__init__.py
ant31box/asyncutils.py
ant31box/client/__init__.py
ant31box/client/base.py
ant31box/client/filedl.py
ant31box/clients.py
ant31box/cmd/__init__.py
ant31box/cmd/default_config.py
ant31box/cmd/main.py
ant31box/cmd/server.py
ant31box/cmd/version.py
ant31box/config.py
ant31box/importer.py
ant31box/init.py
ant31box/logutils.py
ant31box/main.py
ant31box/models.py
ant31box/s3.py
ant31box/server/api/__init__.py
ant31box/server/api/debug.py
ant31box/server/api/info.py
ant31box/server/exception.py
ant31box/server/middlewares/__init__.py
ant31box/server/middlewares/errors.py
ant31box/server/middlewares/process_time.py
ant31box/server/middlewares/token.py
ant31box/server/server.py
ant31box/server/utils.py
ant31box/utilsd.py
ant31box/version.py
ant31box-0.2.8.dist-info/LICENSE
ant31box-0.2.8.dist-info/METADATA
ant31box-0.2.8.dist-info/WHEEL
ant31box-0.2.8.dist-info/entry_points.txt
ant31box-0.2.8.dist-info/RECORD
