Metadata-Version: 2.3
Name: ant31box
Version: 0.2.8
Summary: 
Author: ant31
Author-email: 2t.antoine@gmail.com
Requires-Python: >=3.12,<4
Classifier: Programming Language :: Python :: 3
Classifier: Programming Language :: Python :: 3.12
Classifier: Programming Language :: Python :: 3.13
Provides-Extra: all
Provides-Extra: cli
Provides-Extra: fastapi
Provides-Extra: s3
Provides-Extra: sentry
Requires-Dist: aiofiles
Requires-Dist: aiohttp-prometheus-exporter
Requires-Dist: aiohttp[speedups]
Requires-Dist: aiohttp_requests
Requires-Dist: aioshutil
Requires-Dist: asyncio
Requires-Dist: boto3 ; extra == "all"
Requires-Dist: boto3 ; extra == "s3"
Requires-Dist: cachetools
Requires-Dist: click (<8.20) ; extra == "all"
Requires-Dist: click (<8.20) ; extra == "cli"
Requires-Dist: fastapi[all] ; extra == "all"
Requires-Dist: fastapi[all] ; extra == "fastapi"
Requires-Dist: paramiko
Requires-Dist: pydantic
Requires-Dist: pydantic-settings
Requires-Dist: python-multipart
Requires-Dist: pyyaml
Requires-Dist: rich ; extra == "all"
Requires-Dist: rich ; extra == "cli"
Requires-Dist: sentry-sdk ; extra == "all"
Requires-Dist: sentry-sdk ; extra == "sentry"
Requires-Dist: starlette-exporter ; extra == "all"
Requires-Dist: starlette-exporter ; extra == "fastapi"
Requires-Dist: typer ; extra == "all"
Requires-Dist: typer ; extra == "cli"
Requires-Dist: typing-extensions
